calendrier/__init__.py
calendrier/calendrier.py
mon_calendrier-0.1.dist-info/METADATA
mon_calendrier-0.1.dist-info/WHEEL
mon_calendrier-0.1.dist-info/top_level.txt
mon_calendrier-0.1.dist-info/RECORD
