Metadata-Version: 2.1
Name: mon-calendrier
Version: 0.1
Summary: Une bibliothèque simple pour gérer un calendrier.
Home-page: https://github.com/Adrizen89/calendarAPI
Author: Adrien Berard 
Author-email: adrienberard@hotmail.fr
Classifier: Programming Language :: Python
Classifier: Programming Language :: Python :: 3.12
Classifier: License :: OSI Approved :: MIT License
